LICENSE
django_url_security/__init__.py
django_url_security/core.py
django_url_security/django_url_security.py
django_url_security/generate_permission_spec_file.py
django_url_security/management/commands/export_url_security_file.py
django_url_security/py.typed
django_url_security/url_security.py
django_url_security-0.0.2.dist-info/LICENSE
django_url_security-0.0.2.dist-info/METADATA
django_url_security-0.0.2.dist-info/WHEEL
django_url_security-0.0.2.dist-info/RECORD
