Metadata-Version: 2.1
Name: django-url-security
Version: 0.0.2
Summary: Django URL Security provides tests to ensure all the private endpoints in your Django project are private.
Home-page: https://github.com/Edrolo/django-url-security
License: MIT
Author: Matt Fisher
Author-email: m@ttfisher.com
Requires-Python: >=3.8
Classifier: License :: OSI Approved :: MIT License
Classifier: Natural Language :: English
Classifier: Programming Language :: Python :: 3
Classifier: Programming Language :: Python :: 3.8
Classifier: Programming Language :: Python :: 3.9
Classifier: Programming Language :: Python :: 3.10
Classifier: Programming Language :: Python :: 3.11
Requires-Dist: django (>=3.2)
Requires-Dist: importlib_metadata (>=3.4)
Requires-Dist: parameterized (>=0.9)
